<?xml version="1.0" encoding="utf-8" standalone="yes" ?>
<edmx:Edmx Version="1.0" xmlns:edmx="http://schemas.microsoft.com/ado/2007/06/edmx">
	<edmx:DataServices xmlns:m="http://schemas.microsoft.com/ado/2007/08/dataservices/metadata" m:DataServiceVersion="2.0">
		<Schema Namespace="SBP" xmlns:d="http://schemas.microsoft.com/ado/2007/08/dataservices"
			xmlns:m="http://schemas.microsoft.com/ado/2007/08/dataservices/metadata" xmlns="http://schemas.microsoft.com/ado/2008/09/edm">
			<EntityType Name="ACCOUNTType">
				<Key><PropertyRef Name="ACCOUNT_ID"/></Key><Property Name="ACCOUNT_ID" Type="Edm.Int64" Nullable="false"/><Property Name="EMAIL" Type="Edm.String" Nullable="false" MaxLength="50"/><Property Name="PASSWORD" Type="Edm.String" Nullable="false" MaxLength="32"/><Property Name="REGISTERED_ON" Type="Edm.DateTime"/><Property Name="LAST_ONLINE" Type="Edm.DateTime"/><Property Name="IS_VALID" Type="Edm.String" Nullable="false" DefaultValue="T" MaxLength="1"/></EntityType>
			<EntityType Name="ACCOUNT_DEVICEType">
				<Key><PropertyRef Name="ACCOUNT_ID"/><PropertyRef Name="DEVICE_ID"/></Key><Property Name="ACCOUNT_ID" Type="Edm.Int64" Nullable="false"/><Property Name="DEVICE_ID" Type="Edm.Int64" Nullable="false"/><Property Name="CONNECTED_THROUGH" Type="Edm.String" MaxLength="50"/><Property Name="CONNECTED_IP" Type="Edm.String" MaxLength="32"/><Property Name="MINUTE_TO_RECORD_DATA" Type="Edm.Double" DefaultValue="0.2"/><Property Name="SECONDS_TO_UPDATE_DATA" Type="Edm.Int32" DefaultValue="5"/><Property Name="ENABLE_LED" Type="Edm.String" DefaultValue="Y" MaxLength="1"/><Property Name="ENABLE_BUZZER" Type="Edm.String" DefaultValue="Y" MaxLength="1"/><Property Name="REGISTERED_ON" Type="Edm.DateTime"/><Property Name="DEVICE_NAME" Type="Edm.String" MaxLength="1"/><Property Name="LAST_ONLINE" Type="Edm.DateTime"/></EntityType>
			<EntityType Name="USER_PROFILEType">
				<Key><PropertyRef Name="PROFILE_ID"/></Key><Property Name="PROFILE_ID" Type="Edm.Int64" Nullable="false"/><Property Name="ACCOUNT_ID" Type="Edm.Int64" Nullable="false"/><Property Name="GENDER" Type="Edm.String" Nullable="false" MaxLength="1"/><Property Name="NAME" Type="Edm.String" Nullable="false" MaxLength="50"/><Property Name="DOB" Type="Edm.DateTime" Nullable="false"/><Property Name="AGE" Type="Edm.Int32"/><Property Name="IS_ASTHMATIC" Type="Edm.String" Nullable="false" MaxLength="1"/></EntityType>
			<EntityType Name="DEVICEType">
				<Key><PropertyRef Name="DEVICE_ID"/></Key><Property Name="DEVICE_ID" Type="Edm.Int64" Nullable="false"/><Property Name="SENSOR_HUMIDITY" Type="Edm.String" DefaultValue="Y" MaxLength="1"/><Property Name="SENSOR_TEMPERATURE" Type="Edm.String" DefaultValue="Y" MaxLength="1"/><Property Name="SENSOR_BUTTON" Type="Edm.String" DefaultValue="Y" MaxLength="1"/><Property Name="SENSOR_AIR_QUALITY" Type="Edm.String" DefaultValue="Y" MaxLength="1"/><Property Name="ACTUATOR_BUZZER" Type="Edm.String" DefaultValue="Y" MaxLength="1"/><Property Name="ACTUATOR_LED" Type="Edm.String" DefaultValue="Y" MaxLength="1"/><Property Name="ACTUALTOR_DISPLAY" Type="Edm.String" MaxLength="1"/><Property Name="MANUFACTURED_ON" Type="Edm.DateTime"/><Property Name="DEVICE_SN" Type="Edm.String" Nullable="false" MaxLength="6"/></EntityType>
			<EntityType Name="IOT_DATAType">
				<Key><PropertyRef Name="DATA_ID"/></Key><Property Name="DATA_ID" Type="Edm.Int64" Nullable="false"/><Property Name="DEVICE_ID" Type="Edm.Int64" Nullable="false"/><Property Name="ACCOUNT_ID" Type="Edm.Int64" Nullable="false"/><Property Name="TEMPERATURE" Type="Edm.Double"/><Property Name="HUMIDITY" Type="Edm.Double"/><Property Name="PM2_5" Type="Edm.Double"/><Property Name="PM10" Type="Edm.Double"/><Property Name="COMFORT_LEVEL" Type="Edm.String" MaxLength="1"/><Property Name="DATETIME" Type="Edm.DateTime"/><Property Name="ALERTED" Type="Edm.String" DefaultValue="N" MaxLength="1"/><Property Name="GEO_LOCATION" Type="Edm.String" MaxLength="50"/></EntityType>
			<EntityContainer Name="smartbackpack" m:IsDefaultEntityContainer="true"><EntitySet Name="ACCOUNT" EntityType="SBP.ACCOUNTType"/><EntitySet Name="ACCOUNT_DEVICE" EntityType="SBP.ACCOUNT_DEVICEType"/><EntitySet Name="USER_PROFILE" EntityType="SBP.USER_PROFILEType"/><EntitySet Name="DEVICE" EntityType="SBP.DEVICEType"/><EntitySet Name="IOT_DATA" EntityType="SBP.IOT_DATAType"/></EntityContainer>
		</Schema>
	</edmx:DataServices>
</edmx:Edmx>